lookatme/contrib/grapheasy.py
lookatme.contrib.grapheasy-1.0.0.dist-info/LICENSE
lookatme.contrib.grapheasy-1.0.0.dist-info/METADATA
lookatme.contrib.grapheasy-1.0.0.dist-info/WHEEL
lookatme.contrib.grapheasy-1.0.0.dist-info/top_level.txt
lookatme.contrib.grapheasy-1.0.0.dist-info/RECORD
