Metadata-Version: 2.1
Name: lookatme.contrib.grapheasy
Version: 1.0.0
Summary: Plugin for lookatme providing support for graph-easy.
Home-page: https://github.com/codybuell/lookatme.contrib.grapheasy
Author: Cody Buell
Author-email: cody@codybuell.com
License: MIT
Platform: UNKNOWN
Classifier: License :: OSI Approved :: MIT License
Classifier: Programming Language :: Python :: 3
Classifier: Programming Language :: Python :: 3.9
Classifier: Environment :: Console
Classifier: Environment :: Plugins
Classifier: Operating System :: OS Independent
Classifier: Topic :: Multimedia :: Graphics :: Presentation
Classifier: Topic :: Software Development :: Documentation
Requires-Python: >=3.9
License-File: LICENSE
Requires-Dist: lookatme (<3.0.0,>=2.0.0)
